[
  {
    "url": "https://github.com/isl-org/Open3D",
    "category": "visualization",
    "metadata": [
      "Rhino, Grasshopper",
      "Open3D",
      "3d",
      "3d-perception",
      "arm",
      "computer-graphics",
      "cpp",
      "cuda",
      "gpu",
      "gui",
      "machine-learning",
      "mesh-processing",
      "odometry",
      "opengl",
      "pointcloud",
      "python",
      "pytorch",
      "reconstruction",
      "registration",
      "rendering",
      "tensorflow",
      "visualization"
    ],
    "name": "Open3D",
    "description": "Open3D: A Modern Library for 3D Data Processing",
    "stars": 12399,
    "forks": 2425,
    "lastUpdated": "2025-06-05T18:48:25Z",
    "mainLanguage": "C++",
    "license": "NOASSERTION",
    "topics": [
      "3d",
      "3d-perception",
      "arm",
      "computer-graphics",
      "cpp",
      "cuda",
      "gpu",
      "gui",
      "machine-learning",
      "mesh-processing",
      "odometry",
      "opengl",
      "pointcloud",
      "python",
      "pytorch",
      "reconstruction",
      "registration",
      "rendering",
      "tensorflow",
      "visualization"
    ],
    "openIssues": 1275
  },
  {
    "url": "https://github.com/Open-Cascade-SAS/OCCT",
    "category": "visualization",
    "metadata": [
      "Rhino, Grasshopper",
      "Open Cascade Technology",
      "3d",
      "3d-cad",
      "cad",
      "cae",
      "cam",
      "occt",
      "occt3d",
      "opencascade"
    ],
    "name": "OCCT",
    "description": "Open CASCADE Technology (OCCT) is an open-source software development platform for 3D CAD, CAM, CAE.",
    "stars": 1582,
    "forks": 414,
    "lastUpdated": "2025-06-05T18:17:42Z",
    "mainLanguage": "C++",
    "license": "LGPL-2.1",
    "topics": [
      "3d",
      "3d-cad",
      "cad",
      "cae",
      "cam",
      "occt",
      "occt3d",
      "opencascade"
    ],
    "openIssues": 81
  },
  {
    "url": "https://github.com/compas-dev/compas",
    "category": "interoperability",
    "metadata": [
      "rhino",
      "production",
      "aec",
      "blender3d",
      "data",
      "datastructures",
      "geometry",
      "grasshopper3d",
      "rhino3d",
      "rpc"
    ],
    "submissionDate": "2025-05-22",
    "name": "compas",
    "description": "Core packages of the COMPAS framework.",
    "stars": 333,
    "forks": 112,
    "lastUpdated": "2025-06-04T14:15:36Z",
    "mainLanguage": "Python",
    "license": "MIT",
    "topics": [
      "aec",
      "blender3d",
      "data",
      "datastructures",
      "geometry",
      "grasshopper3d",
      "rhino3d",
      "rpc"
    ],
    "openIssues": 108
  },
  {
    "url": "https://github.com/mrdoob/three.js",
    "category": "interoperability",
    "metadata": [
      "rhino",
      "production",
      "3d",
      "augmented-reality",
      "canvas",
      "html5",
      "javascript",
      "svg",
      "virtual-reality",
      "webaudio",
      "webgl",
      "webgl2",
      "webgpu",
      "webxr"
    ],
    "submissionDate": "2025-05-22",
    "name": "three.js",
    "description": "JavaScript 3D Library.",
    "stars": 106534,
    "forks": 35792,
    "lastUpdated": "2025-06-06T00:43:57Z",
    "mainLanguage": "JavaScript",
    "license": "MIT",
    "topics": [
      "3d",
      "augmented-reality",
      "canvas",
      "html5",
      "javascript",
      "svg",
      "virtual-reality",
      "webaudio",
      "webgl",
      "webgl2",
      "webgpu",
      "webxr"
    ],
    "openIssues": 571
  },
  {
    "url": "https://github.com/IfcOpenShell/voxelization_toolkit",
    "category": "interoperability",
    "metadata": [
      "voxel",
      "ifc"
    ],
    "submissionDate": "2025-05-22",
    "name": "voxelization_toolkit",
    "description": "Voxelization Toolkit for (IFC) Building Models",
    "stars": 81,
    "forks": 17,
    "lastUpdated": "2025-05-20T10:08:16Z",
    "mainLanguage": "C++",
    "license": "MIT",
    "topics": [],
    "openIssues": 9
  },
  {
    "url": "https://github.com/opensourceBIM/BIMserver",
    "category": "Infrastructure",
    "metadata": [
      "bim",
      "openbim",
      "bim-server",
      "bim-applications",
      "bim-bots",
      "bimserver",
      "buildingsmart",
      "ifc",
      "java"
    ],
    "submissionDate": "2025-05-22",
    "name": "BIMserver",
    "description": "The open source BIMserver platform",
    "stars": 1616,
    "forks": 622,
    "lastUpdated": "2025-06-04T06:39:10Z",
    "mainLanguage": "Java",
    "license": "AGPL-3.0",
    "topics": [
      "bim",
      "bim-applications",
      "bim-bots",
      "bim-server",
      "bimserver",
      "buildingsmart",
      "ifc",
      "java",
      "openbim"
    ],
    "openIssues": 110
  },
  {
    "url": "https://github.com/ladybug-tools/ladybug",
    "category": "Analysis",
    "metadata": [
      "LCA"
    ],
    "submissionDate": "2025-05-23",
    "name": "ladybug",
    "description": "🐞 Core ladybug library for weather data analysis and visualization",
    "stars": 206,
    "forks": 55,
    "lastUpdated": "2025-06-04T19:22:33Z",
    "mainLanguage": "Python",
    "license": "AGPL-3.0",
    "topics": [],
    "openIssues": 7
  },
  {
    "url": "https://github.com/FreeCAD/FreeCAD",
    "category": "Visualization",
    "metadata": [
      "CAD",
      "3d",
      "3d-printing",
      "architecture",
      "bim",
      "cad",
      "cam",
      "coin",
      "engineering",
      "fem",
      "freecad",
      "linux",
      "macos",
      "opencascade",
      "windows"
    ],
    "submissionDate": "2025-05-23",
    "name": "FreeCAD",
    "description": "Official source code of FreeCAD, a free and opensource multiplatform 3D parametric modeler.",
    "stars": 24919,
    "forks": 4588,
    "lastUpdated": "2025-06-06T00:13:51Z",
    "mainLanguage": "C++",
    "license": "NOASSERTION",
    "topics": [
      "3d",
      "3d-printing",
      "architecture",
      "bim",
      "cad",
      "cam",
      "coin",
      "engineering",
      "fem",
      "freecad",
      "linux",
      "macos",
      "opencascade",
      "windows"
    ],
    "openIssues": 3110
  },
  {
    "url": "https://github.com/IfcOpenShell/ifcopenshell-jupyter",
    "category": "Development Tools",
    "metadata": [
      "Jupyter Notebook",
      "IfcOpenShell"
    ],
    "submissionDate": "2025-05-23",
    "name": "ifcopenshell-jupyter",
    "description": "Binder to run IfcOpenShell with Jupyter",
    "stars": 3,
    "forks": 0,
    "lastUpdated": "2024-01-18T18:34:12Z",
    "mainLanguage": "Python",
    "license": "Unknown",
    "topics": [],
    "openIssues": 1
  },
  {
    "url": "https://github.com/xBimTeam/XbimEssentials",
    "category": "Sustainability",
    "metadata": [
      "bim",
      "cobie",
      "express",
      "ifc",
      "ifc2x3",
      "ifc4",
      "iso16739",
      "openbim",
      "step21"
    ],
    "submissionDate": "2025-05-24",
    "name": "XbimEssentials",
    "description": "A .NET library to work with data in the IFC format. This is the core component of the Xbim Toolkit",
    "stars": 525,
    "forks": 174,
    "lastUpdated": "2025-06-01T16:33:20Z",
    "mainLanguage": "C#",
    "license": "NOASSERTION",
    "topics": [
      "bim",
      "cobie",
      "express",
      "ifc",
      "ifc2x3",
      "ifc4",
      "iso16739",
      "openbim",
      "step21"
    ],
    "openIssues": 113
  },
  {
    "url": "https://github.com/specklesystems/speckle-server",
    "category": "BIM Tools",
    "metadata": [
      "3d",
      "aec",
      "frontend",
      "interoperability",
      "javascript",
      "monorepo",
      "speckle",
      "speckle-server",
      "threejs",
      "version-control",
      "viewer"
    ],
    "submissionDate": "2025-05-24",
    "name": "speckle-server",
    "description": "The Speckle Server, Frontend, 3D Viewer, & other JS utilities.",
    "stars": 725,
    "forks": 202,
    "lastUpdated": "2025-06-05T13:24:40Z",
    "mainLanguage": "TypeScript",
    "license": "NOASSERTION",
    "topics": [
      "3d",
      "aec",
      "frontend",
      "interoperability",
      "javascript",
      "monorepo",
      "speckle",
      "speckle-server",
      "threejs",
      "version-control",
      "viewer"
    ],
    "openIssues": 101
  },
  {
    "url": "https://github.com/OpenFOAM/OpenFOAM-dev",
    "category": "Development",
    "metadata": [
      "Development Tools",
      "CFD"
    ],
    "submissionDate": "2025-05-24",
    "name": "OpenFOAM-dev",
    "description": "OpenFOAM Foundation development repository",
    "stars": 1732,
    "forks": 635,
    "lastUpdated": "2025-06-06T01:17:52Z",
    "mainLanguage": "C++",
    "license": "NOASSERTION",
    "topics": [],
    "openIssues": 6
  },
  {
    "url": "https://github.com/qgis/QGIS",
    "category": "Sustainability",
    "metadata": [
      "GIS",
      "open-source",
      "mapping"
    ],
    "submissionDate": "2025-05-24",
    "name": "QGIS",
    "description": "QGIS is a free, open source, cross platform (lin/win/mac) geographical information system (GIS)",
    "stars": 11391,
    "forks": 3140,
    "lastUpdated": "2025-06-06T01:22:57Z",
    "mainLanguage": "C++",
    "license": "GPL-2.0",
    "topics": [],
    "openIssues": 4932
  },
  {
    "url": "https://github.com/mcneel/rhino3dm",
    "category": "Development Tools",
    "metadata": [
      "Geometry",
      "Rhino",
      "3D-Modeling",
      "hacktoberfest",
      "javascript-library",
      "opennurbs",
      "python",
      "python3",
      "rhino3d",
      "rhinocommon",
      "wasm"
    ],
    "submissionDate": "2025-05-25",
    "name": "rhino3dm",
    "description": "Libraries based on OpenNURBS with a RhinoCommon style",
    "stars": 657,
    "forks": 141,
    "lastUpdated": "2025-06-02T09:41:19Z",
    "mainLanguage": "C#",
    "license": "MIT",
    "topics": [
      "hacktoberfest",
      "javascript-library",
      "opennurbs",
      "python",
      "python3",
      "rhino3d",
      "rhinocommon",
      "wasm"
    ],
    "openIssues": 23
  },
  {
    "url": "https://github.com/ocni-dtu/lcax",
    "category": "Infrastructure",
    "metadata": [
      "valid-tag",
      "ifc"
    ],
    "submissionDate": "2025-05-25",
    "name": "lcax",
    "description": "LCAx is a open, verifiable, machine and human-readable LCA exchange format",
    "stars": 65,
    "forks": 4,
    "lastUpdated": "2025-05-15T17:27:30Z",
    "mainLanguage": "Rust",
    "license": "Apache-2.0",
    "topics": [],
    "openIssues": 15
  },
  {
    "url": "https://github.com/herzogdemeuron/calc",
    "category": "Sustainability",
    "metadata": [
      "calculation"
    ],
    "submissionDate": "2025-05-26",
    "name": "calc",
    "description": "Calc helps architects quickly estimate the environmental impact of their early design.",
    "stars": 15,
    "forks": 4,
    "lastUpdated": "2025-05-28T08:17:13Z",
    "mainLanguage": "C#",
    "license": "MIT",
    "topics": [],
    "openIssues": 0
  },
  {
    "url": "https://github.com/ifcopenshell/ifcopenshell",
    "category": "Analysis",
    "metadata": [
      "Geo"
    ],
    "submissionDate": "2025-05-26",
    "name": "IfcOpenShell",
    "description": "Open source IFC library and geometry engine",
    "stars": 2117,
    "forks": 788,
    "lastUpdated": "2025-06-05T23:47:46Z",
    "mainLanguage": "C++",
    "license": "LGPL-3.0",
    "topics": [],
    "openIssues": 1000
  },
  {
    "url": "https://github.com/xeokit/xeokit-sdk",
    "category": "Development Tools",
    "metadata": [
      "sdk",
      "3d-tiles",
      "3d-viewers",
      "bim",
      "bim-viewer",
      "buildingsmart",
      "geometry",
      "geospatial",
      "gis",
      "ifc",
      "ifc-viewer",
      "javascript-viewer",
      "las-viewer",
      "laz-viewer",
      "online-viewer",
      "point-cloud",
      "point-cloud-viewer",
      "viewer-sdk",
      "web-viewer",
      "webgl",
      "webgl-viewer"
    ],
    "submissionDate": "2025-05-26",
    "name": "xeokit-sdk",
    "description": "3D BIM IFC Viewer SDK for AEC engineering applications. Open Source JavaScript Toolkit based on pure WebGL for top performance, real-world coordinates and full double precision",
    "stars": 794,
    "forks": 307,
    "lastUpdated": "2025-06-04T22:36:31Z",
    "mainLanguage": "JavaScript",
    "license": "AGPL-3.0",
    "topics": [
      "3d-tiles",
      "3d-viewers",
      "bim",
      "bim-viewer",
      "buildingsmart",
      "geometry",
      "geospatial",
      "gis",
      "ifc",
      "ifc-viewer",
      "javascript-viewer",
      "las-viewer",
      "laz-viewer",
      "online-viewer",
      "point-cloud",
      "point-cloud-viewer",
      "viewer-sdk",
      "web-viewer",
      "webgl",
      "webgl-viewer"
    ],
    "openIssues": 151
  },
  {
    "url": "https://github.com/petrasvestartas/compas_wood",
    "category": "Development Tools",
    "metadata": [
      "wood",
      "timber",
      "cgal",
      "cnc",
      "compas",
      "connections",
      "connector",
      "cpp",
      "integral-mechanical-attachment",
      "joinery",
      "python",
      "robot",
      "structures",
      "timber-structures",
      "woodwork",
      "woodworking"
    ],
    "submissionDate": "2025-05-29",
    "name": "compas_wood",
    "description": "Project for Timber Joint Generation. Documentation:",
    "stars": 40,
    "forks": 2,
    "lastUpdated": "2025-04-26T08:37:52Z",
    "mainLanguage": "Python",
    "license": "MIT",
    "topics": [
      "cgal",
      "cnc",
      "compas",
      "connections",
      "connector",
      "cpp",
      "integral-mechanical-attachment",
      "joinery",
      "python",
      "robot",
      "structures",
      "timber",
      "timber-structures",
      "wood",
      "woodwork",
      "woodworking"
    ],
    "openIssues": 7
  },
  {
    "url": "https://github.com/ladybug-tools/honeybee-energy",
    "category": "Analysis",
    "metadata": [
      "simulation",
      "energy"
    ],
    "submissionDate": "2025-05-29",
    "name": "honeybee-energy",
    "description": "🐝 :fire: Honeybee extension for energy simulation",
    "stars": 33,
    "forks": 18,
    "lastUpdated": "2025-06-04T22:01:10Z",
    "mainLanguage": "Python",
    "license": "AGPL-3.0",
    "topics": [],
    "openIssues": 20
  },
  {
    "url": "https://github.com/ladybug-tools/dragonfly-core",
    "category": "Parametric Design",
    "metadata": [
      "analysis",
      "test"
    ],
    "name": "dragonfly-core",
    "description": ":dragon: dragonfly core library",
    "stars": 18,
    "forks": 12,
    "lastUpdated": "2025-06-05T21:24:05Z",
    "mainLanguage": "Python",
    "license": "AGPL-3.0",
    "topics": [],
    "submissionDate": "2025-05-29",
    "openIssues": 1
  },
  {
    "url": "https://github.com/ladybug-tools/honeybee-radiance",
    "category": "Development Tools",
    "metadata": [
      "Radiance",
      "test"
    ],
    "name": "honeybee-radiance",
    "description": "🐝 ⚡️ Radiance extension for Honeybee",
    "stars": 16,
    "forks": 10,
    "lastUpdated": "2025-06-04T19:49:03Z",
    "mainLanguage": "Python",
    "license": "AGPL-3.0",
    "topics": [],
    "submissionDate": "2025-05-29",
    "openIssues": 9
  },
  {
    "url": "https://github.com/TheVessen/geospiza",
    "category": "Parametric Design",
    "metadata": [
      "generativeDesign",
      "computational-design",
      "evolutionary-algorithms",
      "grasshopper",
      "rhino"
    ],
    "name": "geospiza",
    "description": "Geospiza is a project focusing on evolutionary design in grasshopper",
    "stars": 5,
    "forks": 0,
    "lastUpdated": "2025-02-25T17:10:28Z",
    "mainLanguage": "C#",
    "license": "MIT",
    "topics": [
      "computational-design",
      "evolutionary-algorithms",
      "grasshopper",
      "rhino"
    ],
    "submissionDate": "2025-05-29",
    "openIssues": 5
  },
  {
    "url": "https://github.com/NREL/OpenStudio",
    "category": "Analysis",
    "metadata": [
      "Energy modeling",
      "HVAC systems",
      "Simulation"
    ],
    "name": "OpenStudio",
    "description": "OpenStudio is a cross-platform collection of software tools to support whole building energy modeling using EnergyPlus and advanced daylight analysis using Radiance.",
    "stars": 542,
    "forks": 214,
    "lastUpdated": "2025-06-05T07:01:01Z",
    "mainLanguage": "C++",
    "license": "NOASSERTION",
    "topics": [],
    "openIssues": 197
  },
  {
    "url": "https://github.com/boydhont/BetterCorrectFast",
    "category": "BIM Tools",
    "metadata": [
      "architecture"
    ],
    "name": "BetterCorrectFast",
    "description": "Simplified BIM Collaboration Format (BCF) generation for project leaders and managers",
    "stars": 12,
    "forks": 0,
    "lastUpdated": "2025-02-13T12:50:50Z",
    "mainLanguage": "Python",
    "license": "MIT",
    "topics": [],
    "submissionDate": "2025-06-01",
    "openIssues": 1
  },
  {
    "url": "https://github.com/PerkinsAndWill-IO/sPrint",
    "category": "Visualization",
    "metadata": [
      "Printing",
      "document",
      "ifc",
      "bim",
      "web"
    ],
    "name": "sPrint",
    "description": "A Chrome extension that allows batch-print PDFs from BIM360 and ACC platforms.",
    "stars": 31,
    "forks": 5,
    "lastUpdated": "2024-12-19T15:23:17Z",
    "mainLanguage": "TypeScript",
    "license": "MIT",
    "topics": [],
    "submissionDate": "2025-06-05",
    "openIssues": 3
  },
  {
    "url": "https://github.com/ThatOpen/engine_web-ifc",
    "category": "Interoperability",
    "metadata": [
      "web",
      "ifc",
      "cpp",
      "emscripten",
      "javascript",
      "wasm",
      "webassembly"
    ],
    "name": "engine_web-ifc",
    "description": "Reading and writing IFC files with Javascript, at native speeds.",
    "stars": 732,
    "forks": 217,
    "lastUpdated": "2025-06-05T10:14:39Z",
    "mainLanguage": "TypeScript",
    "license": "MPL-2.0",
    "topics": [
      "cpp",
      "emscripten",
      "ifc",
      "javascript",
      "wasm",
      "webassembly"
    ],
    "submissionDate": "2025-06-05",
    "openIssues": 70
  }
]